rtl/sync_fifo.sv
module sync_fifo #(
    parameter data_width=8,
    parameter fifo_depth=16
     )
    //port list 
    (input logic [data_width-1:0] data_in,
    input logic clk,
    input logic rst_n,
    input logic wr_en,
    input logic rd_en,
    output logic [data_width-1:0] data_out,
    output logic full,
    output logic empty
);
localparam width= $clog2(fifo_depth);
logic [width:0] wr_ptr;
logic [width:0] rd_ptr;
logic [data_width-1:0] memory [fifo_depth];
always_ff @(posedge clk or negedge rst_n) begin
if (!rst_n) begin
wr_ptr<=0;
rd_ptr<=0;
data_out<=0;
end
else begin
if (wr_en==1 && full==0) begin
memory[wr_ptr[width-1:0]]<= data_in;
wr_ptr <= wr_ptr + 1;
end
if (rd_en==1 && empty==0)begin
data_out<=memory[rd_ptr[width-1:0]];
rd_ptr <= rd_ptr + 1;
end
end
end
assign empty = (wr_ptr == rd_ptr);
assign full  = (wr_ptr[width] != rd_ptr[width]) && (wr_ptr[width-1:0] == rd_ptr[width-1:0]);

endmodule

tb/sync_fifo_tb.sv
`timescale 1ns/1ps
module sync_fifo_tb;
logic clk;
logic rst_n;
logic wr_en;
logic rd_en;
logic full;
logic empty;
logic [7:0] data_in;
logic [7:0] data_out;
initial begin
clk=0;
forever #5 clk=~clk;
end
sync_fifo dut(
    .clk(clk),
    .rst_n(rst_n),
    .wr_en(wr_en),
    .rd_en(rd_en),
    .full(full),
    .empty(empty),
    .data_in(data_in),
    .data_out(data_out)

); 
initial begin
rst_n=0;wr_en=0;rd_en=0;data_in=0;
@(posedge clk); @(posedge clk);
rst_n=1;
repeat (16) begin
@(posedge clk);
wr_en=1;
data_in=data_in+1;
end
wr_en=0;
@(posedge clk);
wr_en=1;data_in=8'hFF;
@(posedge clk);
wr_en=0;
repeat (16) begin
@(posedge clk);
rd_en=1;
end
rd_en=0;
@(posedge clk);
    wr_en = 1; rd_en = 1; data_in = 8'hAA;
    @(posedge clk);
    wr_en = 0; rd_en = 0;
@(posedge clk);
    wr_en = 1; data_in = 8'h55;
    @(posedge clk);
    rst_n = 0;
    @(posedge clk);
    rst_n = 1;
    wr_en = 0;
#20 $finish;        
end   
initial begin
    $dumpfile("sim/sync_fifo.vcd");
    $dumpvars(0, sync_fifo_tb);
end


endmodule

sim/sync_fifo.vcd
$date
	Tue Jul 21 19:37:31 2026
$end
$version
	Icarus Verilog
$end
$timescale
	1ps
$end
$scope module sync_fifo_tb $end
$var wire 1 ! full $end
$var wire 1 " empty $end
$var wire 8 # data_out [7:0] $end
$var reg 1 $ clk $end
$var reg 8 % data_in [7:0] $end
$var reg 1 & rd_en $end
$var reg 1 ' rst_n $end
$var reg 1 ( wr_en $end
$scope module dut $end
$var wire 1 $ clk $end
$var wire 8 ) data_in [7:0] $end
$var wire 1 ! full $end
$var wire 1 & rd_en $end
$var wire 1 ' rst_n $end
$var wire 1 ( wr_en $end
$var wire 1 " empty $end
$var parameter 32 * data_width $end
$var parameter 32 + fifo_depth $end
$var parameter 32 , width $end
$var reg 8 - data_out [7:0] $end
$var reg 5 . rd_ptr [4:0] $end
$var reg 5 / wr_ptr [4:0] $end
$upscope $end
$upscope $end
$enddefinitions $end
$comment Show the parameter values. $end
$dumpall
b100 ,
b10000 +
b1000 *
$end
#0
$dumpvars
b0 /
b0 .
b0 -
b0 )
0(
0'
0&
b0 %
0$
b0 #
1"
0!
$end
#5000
1$
#10000
0$
#15000
1'
1$
#20000
0$
#25000
0"
b1 /
b1 %
b1 )
1(
1$
#30000
0$
#35000
b10 /
b10 %
b10 )
1$
#40000
0$
#45000
b11 /
b11 %
b11 )
1$
#50000
0$
#55000
b100 /
b100 %
b100 )
1$
#60000
0$
#65000
b101 /
b101 %
b101 )
1$
#70000
0$
#75000
b110 /
b110 %
b110 )
1$
#80000
0$
#85000
b111 /
b111 %
b111 )
1$
#90000
0$
#95000
b1000 /
b1000 %
b1000 )
1$
#100000
0$
#105000
b1001 /
b1001 %
b1001 )
1$
#110000
0$
#115000
b1010 /
b1010 %
b1010 )
1$
#120000
0$
#125000
b1011 /
b1011 %
b1011 )
1$
#130000
0$
#135000
b1100 /
b1100 %
b1100 )
1$
#140000
0$
#145000
b1101 /
b1101 %
b1101 )
1$
#150000
0$
#155000
b1110 /
b1110 %
b1110 )
1$
#160000
0$
#165000
b1111 /
b1111 %
b1111 )
1$
#170000
0$
#175000
0(
b10000 %
b10000 )
1$
#180000
0$
#185000
1!
b10000 /
b11111111 %
b11111111 )
1(
1$
#190000
0$
#195000
0(
1$
#200000
0$
#205000
0!
b1 .
b1 #
b1 -
1&
1$
#210000
0$
#215000
b10 .
b10 #
b10 -
1$
#220000
0$
#225000
b11 .
b11 #
b11 -
1$
#230000
0$
#235000
b100 .
b100 #
b100 -
1$
#240000
0$
#245000
b101 .
b101 #
b101 -
1$
#250000
0$
#255000
b110 .
b110 #
b110 -
1$
#260000
0$
#265000
b111 .
b111 #
b111 -
1$
#270000
0$
#275000
b1000 .
b1000 #
b1000 -
1$
#280000
0$
#285000
b1001 .
b1001 #
b1001 -
1$
#290000
0$
#295000
b1010 .
b1010 #
b1010 -
1$
#300000
0$
#305000
b1011 .
b1011 #
b1011 -
1$
#310000
0$
#315000
b1100 .
b1100 #
b1100 -
1$
#320000
0$
#325000
b1101 .
b1101 #
b1101 -
1$
#330000
0$
#335000
b1110 .
b1110 #
b1110 -
1$
#340000
0$
#345000
b1111 .
b1111 #
b1111 -
1$
#350000
0$
#355000
0&
1$
#360000
0$
#365000
b10000 .
b11111111 #
b11111111 -
b10001 /
b10101010 %
b10101010 )
1&
1(
1$
#370000
0$
#375000
0&
0(
1$
#380000
0$
#385000
b10010 /
b1010101 %
b1010101 )
1(
1$
#390000
0$
#395000
b0 #
b0 -
1"
b0 .
b0 /
0'
1$
#400000
0$
#405000
0(
1'
1$
